twitchAPI/__init__.py
twitchAPI/helper.py
twitchAPI/oauth.py
twitchAPI/pubsub.py
twitchAPI/py.typed
twitchAPI/twitch.py
twitchAPI/type.py
twitchAPI/chat/__init__.py
twitchAPI/chat/middleware.py
twitchAPI/eventsub/__init__.py
twitchAPI/eventsub/base.py
twitchAPI/eventsub/webhook.py
twitchAPI/eventsub/websocket.py
twitchAPI/object/__init__.py
twitchAPI/object/api.py
twitchAPI/object/base.py
twitchAPI/object/eventsub.py
twitchAPI-4.3.1.dist-info/LICENSE.txt
twitchAPI-4.3.1.dist-info/METADATA
twitchAPI-4.3.1.dist-info/WHEEL
twitchAPI-4.3.1.dist-info/top_level.txt
twitchAPI-4.3.1.dist-info/zip-safe
twitchAPI-4.3.1.dist-info/RECORD
