Metadata-Version: 2.1
Name: twitchAPI
Version: 4.3.1
Summary: A Python 3.7+ implementation of the Twitch Helix API, PubSub, EventSub and Chat
Home-page: https://github.com/Teekeks/pyTwitchAPI
Author: Lena "Teekeks" During
Author-email: info@teawork.de
License: MIT
Keywords: twitch,twitch.tv,chat,bot,event sub,EventSub,pub sub,PubSub,helix,api
Classifier: Development Status :: 5 - Production/Stable
Classifier: Intended Audience :: Developers
Classifier: Topic :: Communications
Classifier: Topic :: Software Development :: Libraries
Classifier: Topic :: Software Development :: Libraries :: Python Modules
Classifier: Topic :: Software Development :: Libraries :: Application Frameworks
Classifier: License :: OSI Approved :: MIT License
Classifier: Programming Language :: Python
Classifier: Programming Language :: Python :: 3
Classifier: Programming Language :: Python :: 3.7
Classifier: Programming Language :: Python :: 3.8
Classifier: Programming Language :: Python :: 3.9
Classifier: Programming Language :: Python :: 3.10
Classifier: Programming Language :: Python :: 3.11
Classifier: Programming Language :: Python :: 3.12
License-File: LICENSE.txt
Requires-Dist: aiohttp>=3.9.3
Requires-Dist: python-dateutil>=2.8.2
Requires-Dist: typing-extensions
Requires-Dist: enum-tools
